tfy_assistant_framework/__init__.py
tfy_assistant_framework/_http_client.py
tfy_assistant_framework/_logger.py
tfy_assistant_framework/nats_client.py
tfy_assistant_framework/settings.py
tfy_assistant_framework/assistant/__init__.py
tfy_assistant_framework/assistant/_assistant_runner.py
tfy_assistant_framework/assistant/_assistant_tasks.py
tfy_assistant_framework/assistant/_base_assistant_io.py
tfy_assistant_framework/assistant/_console_assistant_io.py
tfy_assistant_framework/assistant/_nats_assistant_io.py
tfy_assistant_framework/assistant/_serve.py
tfy_assistant_framework/assistant/_types.py
tfy_assistant_framework/swarm/README.md
tfy_assistant_framework/swarm/__init__.py
tfy_assistant_framework/swarm/_core.py
tfy_assistant_framework/swarm/_logger.py
tfy_assistant_framework/swarm/_types.py
tfy_assistant_framework-0.1.10.dist-info/METADATA
tfy_assistant_framework-0.1.10.dist-info/WHEEL
tfy_assistant_framework-0.1.10.dist-info/RECORD
