Metadata-Version: 2.4
Name: tfy_assistant_framework
Version: 0.1.10
Summary: Framework for building AI assistants with streaming updates and user interactions
Project-URL: Homepage, https://github.com/truefoundry/tfy_assistant_framework
Project-URL: Repository, https://github.com/truefoundry/tfy_assistant_framework
Requires-Python: >=3.12
Requires-Dist: aiohttp<4.0.0,>=3.11.11
Requires-Dist: fastapi<1.0.0,>=0.115.6
Requires-Dist: httpx<1.0.0,>=0.28.1
Requires-Dist: logfire<4.0.0,>=3.4.0
Requires-Dist: nats-py[nkeys]<3.0.0,>=2.10.0
Requires-Dist: openai<2.0.0,>=1.58.1
Requires-Dist: pydantic-settings<3.0.0,>=2.7.0
Requires-Dist: pydantic<3.0.0,>=2.10.4
Requires-Dist: python-dotenv<2.0.0,>=1.0.1
Requires-Dist: rich<14.0.0,>=13.9.4
Requires-Dist: uvicorn<1.0.0,>=0.27.1
